tvb/__init__.py
tvb/config/__init__.py
tvb/config/algorithm_categories.py
tvb/config/profile_settings.py
tvb/config/init/__init__.py
tvb/config/init/datatypes_registry.py
tvb/config/init/initializer.py
tvb/config/init/introspector_registry.py
tvb/config/init/model_manager.py
tvb/config/init/alembic/env.py
tvb/config/init/alembic/versions/32d4bf9f8cab_update_db_002.py
tvb/config/init/alembic/versions/32d4bf9f8def_update_db_003.py
tvb/config/init/alembic/versions/32d4bf9f8ghj_update_db_004.py
tvb/config/init/alembic/versions/__init__.py
tvb/config/init/alembic/versions/ec2859bb9114_update_db_001.py
tvb/config/logger/__init__.py
tvb/config/logger/cluster_handler.py
tvb/config/logger/dev_logger_config.conf
tvb/config/logger/elasticsearch_handler.py
tvb/config/logger/logger_config.conf
tvb/interfaces/__init__.py
tvb/interfaces/rest/__init__.py
tvb/interfaces/rest/bids_monitor/__init__.py
tvb/interfaces/rest/bids_monitor/bids_data_builder.py
tvb/interfaces/rest/bids_monitor/bids_dir_monitor.py
tvb/interfaces/rest/bids_monitor/launch_bids_monitor.py
tvb/interfaces/rest/bids_monitor/tests/__init__.py
tvb/interfaces/rest/bids_monitor/tests/bids_monitor_test.py
tvb_bids_monitor-2.9.dist-info/AUTHORS
tvb_bids_monitor-2.9.dist-info/LICENSE
tvb_bids_monitor-2.9.dist-info/METADATA
tvb_bids_monitor-2.9.dist-info/WHEEL
tvb_bids_monitor-2.9.dist-info/top_level.txt
tvb_bids_monitor-2.9.dist-info/RECORD
