Metadata-Version: 2.1
Name: tvb-bids-monitor
Version: 2.9
Summary: A helper package containing BIDS directory monitor module
Home-page: https://www.thevirtualbrain.org
Download-URL: https://github.com/the-virtual-brain/tvb-root
Author: Akash Upadhyay, Paula Prodan
Author-email: tvb.admin@thevirtualbrain.org
License: GPL-3.0-or-later
Keywords: tvb rest client brain simulator neuroscience human animal neuronal dynamics models delay
License-File: LICENSE
License-File: AUTHORS
Requires-Dist: tvb-rest-client
Requires-Dist: watchdog
Provides-Extra: test
Requires-Dist: pytest ; extra == 'test'
Requires-Dist: pytest-benchmark ; extra == 'test'
